qrcode_xcolor/__init__.py
qrcode_xcolor-0.1.1.dist-info/LICENSE
qrcode_xcolor-0.1.1.dist-info/METADATA
qrcode_xcolor-0.1.1.dist-info/WHEEL
qrcode_xcolor-0.1.1.dist-info/top_level.txt
qrcode_xcolor-0.1.1.dist-info/RECORD
