Metadata-Version: 2.1
Name: qrcode-xcolor
Version: 0.1.1
Summary: Custom QRCode Modules
Home-page: https://github.com/xtream1101/qrcode-xcolor
License: MIT
License-File: LICENSE
